aiontfy/__init__.py
aiontfy/const.py
aiontfy/exceptions.py
aiontfy/helpers.py
aiontfy/ntfy.py
aiontfy/py.typed
aiontfy/types.py
aiontfy-0.7.0.dist-info/METADATA
aiontfy-0.7.0.dist-info/WHEEL
aiontfy-0.7.0.dist-info/licenses/LICENSE
aiontfy-0.7.0.dist-info/RECORD
