Metadata-Version: 2.4
Name: aiontfy
Version: 0.7.0
Summary: Async ntfy client library
Project-URL: Documentation, https://tr4nt0r.github.io/aiontfy/
Project-URL: Source, https://github.com/tr4nt0r/aiontfy
Author-email: Manfred Dennerlein Rodelo <manfred@dennerlein.name>
License-Expression: MIT
License-File: LICENSE
Classifier: Operating System :: OS Independent
Classifier: Programming Language :: Python :: 3.12
Requires-Python: >=3.12
Requires-Dist: aiohttp~=3.11
Requires-Dist: mashumaro~=3.13
Requires-Dist: orjson~=3.10
